{
  "categoryList": ["New", "Men", "Women", "Kids"],
  "totalList": [
    {
      "id": 40,
      "productName": "Sleek Wooden Pants",
      "productImage": "http://placeimg.com/640/480/fashion",
      "price": 46500,
      "grade": 4.9,
      "category": "men",
      "categoryDetail": "청바지",
      "releaseDate": "2020-05-21T23:24:58.142Z"
    },
    {
      "id": 3,
      "productName": "Licensed Cotton Towels",
      "productImage": "http://placeimg.com/640/480/fashion",
      "price": 65000,
      "grade": 4.9,
      "category": "men",
      "categoryDetail": "신발",
      "releaseDate": "2018-12-23T07:17:46.897Z"
    },
    {
      "id": 19,
      "productName": "Handcrafted Granite Chips",
      "productImage": "http://placeimg.com/640/480/fashion",
      "price": 65100,
      "grade": 4.8,
      "category": "men",
      "categoryDetail": "청바지",
      "releaseDate": "2020-09-26T13:37:58.619Z"
    },
    {
      "id": 32,
      "productName": "Gorgeous Steel Computer",
      "productImage": "http://placeimg.com/640/480/fashion",
      "price": 27000,
      "grade": 4.7,
      "category": "new",
      "categoryDetail": "스웨터",
      "releaseDate": "2020-11-28T19:06:27.533Z"
    },
    {
      "id": 21,
      "productName": "Handcrafted Frozen Table",
      "productImage": "http://placeimg.com/640/480/fashion",
      "price": 99300,
      "grade": 4.6,
      "category": "kids",
      "categoryDetail": "청바지",
      "releaseDate": "2018-11-29T11:39:20.068Z"
    },
    {
      "id": 28,
      "productName": "Refined Cotton Sausages",
      "productImage": "http://placeimg.com/640/480/fashion",
      "price": 30400,
      "grade": 4.4,
      "category": "men",
      "categoryDetail": "코트",
      "releaseDate": "2018-10-19T08:31:05.461Z"
    },
    {
      "id": 14,
      "productName": "Licensed Plastic Bike",
      "productImage": "http://placeimg.com/640/480/fashion",
      "price": 42300,
      "grade": 4.3,
      "category": "men",
      "categoryDetail": "신발",
      "releaseDate": "2021-01-20T09:41:06.962Z"
    },
    {
      "id": 5,
      "productName": "Tasty Wooden Sausages",
      "productImage": "http://placeimg.com/640/480/fashion",
      "price": 40600,
      "grade": 4.2,
      "category": "kids",
      "categoryDetail": "코트",
      "releaseDate": "2019-10-29T10:14:55.007Z"
    },
    {
      "id": 44,
      "productName": "Incredible Plastic Soap",
      "productImage": "http://placeimg.com/640/480/fashion",
      "price": 26500,
      "grade": 4.1,
      "category": "new",
      "categoryDetail": "맨투맨",
      "releaseDate": "2018-02-28T12:56:57.444Z"
    },
    {
      "id": 42,
      "productName": "Small Metal Shirt",
      "productImage": "http://placeimg.com/640/480/fashion",
      "price": 800,
      "grade": 3.9,
      "category": "kids",
      "categoryDetail": "코트",
      "releaseDate": "2018-03-10T05:58:13.912Z"
    },
    {
      "id": 25,
      "productName": "Refined Plastic Bike",
      "productImage": "http://placeimg.com/640/480/fashion",
      "price": 51200,
      "grade": 3.8,
      "category": "new",
      "categoryDetail": "코트",
      "releaseDate": "2020-01-17T04:55:54.593Z"
    },
    {
      "id": 34,
      "productName": "Gorgeous Metal Keyboard",
      "productImage": "http://placeimg.com/640/480/fashion",
      "price": 43200,
      "grade": 3.6,
      "category": "new",
      "categoryDetail": "맨투맨",
      "releaseDate": "2020-04-27T19:28:42.949Z"
    },
    {
      "id": 49,
      "productName": "Incredible Frozen Gloves",
      "productImage": "http://placeimg.com/640/480/fashion",
      "price": 1200,
      "grade": 3.5,
      "category": "women",
      "categoryDetail": "스웨터",
      "releaseDate": "2020-09-17T19:13:38.829Z"
    },
    {
      "id": 37,
      "productName": "Gorgeous Metal Soap",
      "productImage": "http://placeimg.com/640/480/fashion",
      "price": 22700,
      "grade": 3.5,
      "category": "women",
      "categoryDetail": "청바지",
      "releaseDate": "2019-02-17T05:13:12.767Z"
    },
    {
      "id": 31,
      "productName": "Handcrafted Fresh Ball",
      "productImage": "http://placeimg.com/640/480/fashion",
      "price": 81400,
      "grade": 3.5,
      "category": "men",
      "categoryDetail": "청바지",
      "releaseDate": "2020-07-07T15:04:10.323Z"
    },
    {
      "id": 18,
      "productName": "Ergonomic Granite Computer",
      "productImage": "http://placeimg.com/640/480/fashion",
      "price": 88900,
      "grade": 3.5,
      "category": "kids",
      "categoryDetail": "코트",
      "releaseDate": "2021-03-09T10:48:33.300Z"
    },
    {
      "id": 41,
      "productName": "Tasty Metal Towels",
      "productImage": "http://placeimg.com/640/480/fashion",
      "price": 83400,
      "grade": 3.4,
      "category": "kids",
      "categoryDetail": "코트",
      "releaseDate": "2018-09-06T22:35:51.639Z"
    },
    {
      "id": 50,
      "productName": "Rustic Concrete Shirt",
      "productImage": "http://placeimg.com/640/480/fashion",
      "price": 28800,
      "grade": 3.2,
      "category": "kids",
      "categoryDetail": "스웨터",
      "releaseDate": "2018-10-17T15:54:41.358Z"
    },
    {
      "id": 13,
      "productName": "Gorgeous Cotton Bike",
      "productImage": "http://placeimg.com/640/480/fashion",
      "price": 78900,
      "grade": 3.2,
      "category": "women",
      "categoryDetail": "맨투맨",
      "releaseDate": "2019-05-05T09:28:23.081Z"
    },
    {
      "id": 1,
      "productName": "Fantastic Fresh Table",
      "productImage": "http://placeimg.com/640/480/fashion",
      "price": 68000,
      "grade": 3.2,
      "category": "women",
      "categoryDetail": "코트",
      "releaseDate": "2019-04-09T23:20:57.443Z"
    },
    {
      "id": 8,
      "productName": "Sleek Frozen Bike",
      "productImage": "http://placeimg.com/640/480/fashion",
      "price": 38700,
      "grade": 3.1,
      "category": "new",
      "categoryDetail": "코트",
      "releaseDate": "2020-09-28T05:35:56.059Z"
    },
    {
      "id": 33,
      "productName": "Refined Metal Salad",
      "productImage": "http://placeimg.com/640/480/fashion",
      "price": 22500,
      "grade": 2.8,
      "category": "men",
      "categoryDetail": "청바지",
      "releaseDate": "2019-12-14T01:47:28.594Z"
    },
    {
      "id": 48,
      "productName": "Refined Frozen Hat",
      "productImage": "http://placeimg.com/640/480/fashion",
      "price": 9200,
      "grade": 2.7,
      "category": "women",
      "categoryDetail": "청바지",
      "releaseDate": "2020-03-19T10:20:29.348Z"
    },
    {
      "id": 22,
      "productName": "Small Frozen Fish",
      "productImage": "http://placeimg.com/640/480/fashion",
      "price": 81600,
      "grade": 2.7,
      "category": "new",
      "categoryDetail": "스웨터",
      "releaseDate": "2019-09-13T11:34:16.258Z"
    },
    {
      "id": 47,
      "productName": "Awesome Plastic Gloves",
      "productImage": "http://placeimg.com/640/480/fashion",
      "price": 14800,
      "grade": 2.5,
      "category": "women",
      "categoryDetail": "스웨터",
      "releaseDate": "2018-10-14T05:00:55.638Z"
    },
    {
      "id": 38,
      "productName": "Tasty Wooden Salad",
      "productImage": "http://placeimg.com/640/480/fashion",
      "price": 82600,
      "grade": 2.5,
      "category": "women",
      "categoryDetail": "맨투맨",
      "releaseDate": "2019-10-24T15:08:58.399Z"
    },
    {
      "id": 24,
      "productName": "Awesome Frozen Chips",
      "productImage": "http://placeimg.com/640/480/fashion",
      "price": 2400,
      "grade": 2.4,
      "category": "women",
      "categoryDetail": "코트",
      "releaseDate": "2020-03-21T13:26:23.898Z"
    },
    {
      "id": 36,
      "productName": "Intelligent Plastic Bacon",
      "productImage": "http://placeimg.com/640/480/fashion",
      "price": 70400,
      "grade": 2.3,
      "category": "new",
      "categoryDetail": "스웨터",
      "releaseDate": "2020-09-11T11:39:58.443Z"
    },
    {
      "id": 45,
      "productName": "Awesome Plastic Salad",
      "productImage": "http://placeimg.com/640/480/fashion",
      "price": 26300,
      "grade": 2.2,
      "category": "new",
      "categoryDetail": "신발",
      "releaseDate": "2018-02-05T20:37:28.106Z"
    },
    {
      "id": 46,
      "productName": "Refined Granite Chicken",
      "productImage": "http://placeimg.com/640/480/fashion",
      "price": 55300,
      "grade": 2,
      "category": "women",
      "categoryDetail": "코트",
      "releaseDate": "2020-09-22T20:51:52.532Z"
    },
    {
      "id": 15,
      "productName": "Ergonomic Concrete Mouse",
      "productImage": "http://placeimg.com/640/480/fashion",
      "price": 97000,
      "grade": 2,
      "category": "kids",
      "categoryDetail": "신발",
      "releaseDate": "2019-10-09T23:41:56.851Z"
    },
    {
      "id": 17,
      "productName": "Handcrafted Metal Chair",
      "productImage": "http://placeimg.com/640/480/fashion",
      "price": 6200,
      "grade": 1.9,
      "category": "new",
      "categoryDetail": "청바지",
      "releaseDate": "2020-01-07T02:19:15.197Z"
    },
    {
      "id": 16,
      "productName": "Handmade Concrete Mouse",
      "productImage": "http://placeimg.com/640/480/fashion",
      "price": 10400,
      "grade": 1.9,
      "category": "kids",
      "categoryDetail": "신발",
      "releaseDate": "2021-04-27T16:57:30.077Z"
    },
    {
      "id": 12,
      "productName": "Licensed Concrete Cheese",
      "productImage": "http://placeimg.com/640/480/fashion",
      "price": 35300,
      "grade": 1.9,
      "category": "men",
      "categoryDetail": "코트",
      "releaseDate": "2019-07-21T20:30:31.463Z"
    },
    {
      "id": 30,
      "productName": "Tasty Frozen Fish",
      "productImage": "http://placeimg.com/640/480/fashion",
      "price": 36900,
      "grade": 1.6,
      "category": "men",
      "categoryDetail": "청바지",
      "releaseDate": "2018-07-18T19:08:52.834Z"
    },
    {
      "id": 23,
      "productName": "Rustic Concrete Ball",
      "productImage": "http://placeimg.com/640/480/fashion",
      "price": 80100,
      "grade": 1.6,
      "category": "new",
      "categoryDetail": "스웨터",
      "releaseDate": "2021-03-23T09:40:24.501Z"
    },
    {
      "id": 20,
      "productName": "Generic Plastic Keyboard",
      "productImage": "http://placeimg.com/640/480/fashion",
      "price": 64500,
      "grade": 1.5,
      "category": "new",
      "categoryDetail": "맨투맨",
      "releaseDate": "2018-11-09T19:30:12.871Z"
    },
    {
      "id": 39,
      "productName": "Sleek Cotton Ball",
      "productImage": "http://placeimg.com/640/480/fashion",
      "price": 64100,
      "grade": 1.3,
      "category": "kids",
      "categoryDetail": "코트",
      "releaseDate": "2020-10-24T13:16:38.631Z"
    },
    {
      "id": 35,
      "productName": "Handmade Soft Car",
      "productImage": "http://placeimg.com/640/480/fashion",
      "price": 97900,
      "grade": 1.3,
      "category": "men",
      "categoryDetail": "코트",
      "releaseDate": "2018-02-21T17:10:39.745Z"
    },
    {
      "id": 26,
      "productName": "Small Wooden Shirt",
      "productImage": "http://placeimg.com/640/480/fashion",
      "price": 66300,
      "grade": 1.3,
      "category": "women",
      "categoryDetail": "신발",
      "releaseDate": "2019-02-17T10:23:35.949Z"
    },
    {
      "id": 4,
      "productName": "Tasty Metal Shoes",
      "productImage": "http://placeimg.com/640/480/fashion",
      "price": 53100,
      "grade": 1.1,
      "category": "new",
      "categoryDetail": "스웨터",
      "releaseDate": "2021-06-15T09:45:12.717Z"
    },
    {
      "id": 7,
      "productName": "Unbranded Wooden Pizza",
      "productImage": "http://placeimg.com/640/480/fashion",
      "price": 97700,
      "grade": 0.9,
      "category": "kids",
      "categoryDetail": "코트",
      "releaseDate": "2020-03-21T06:50:08.374Z"
    },
    {
      "id": 29,
      "productName": "Sleek Cotton Towels",
      "productImage": "http://placeimg.com/640/480/fashion",
      "price": 87600,
      "grade": 0.7,
      "category": "women",
      "categoryDetail": "스웨터",
      "releaseDate": "2020-08-04T03:47:14.231Z"
    },
    {
      "id": 27,
      "productName": "Intelligent Cotton Bike",
      "productImage": "http://placeimg.com/640/480/fashion",
      "price": 22800,
      "grade": 0.7,
      "category": "men",
      "categoryDetail": "맨투맨",
      "releaseDate": "2019-05-16T17:34:19.770Z"
    },
    {
      "id": 10,
      "productName": "Fantastic Steel Shirt",
      "productImage": "http://placeimg.com/640/480/fashion",
      "price": 36400,
      "grade": 0.5,
      "category": "men",
      "categoryDetail": "청바지",
      "releaseDate": "2019-11-19T19:12:01.440Z"
    },
    {
      "id": 43,
      "productName": "Intelligent Plastic Shirt",
      "productImage": "http://placeimg.com/640/480/fashion",
      "price": 47400,
      "grade": 0.2,
      "category": "kids",
      "categoryDetail": "청바지",
      "releaseDate": "2019-01-17T11:06:02.249Z"
    },
    {
      "id": 11,
      "productName": "Sleek Steel Shoes",
      "productImage": "http://placeimg.com/640/480/fashion",
      "price": 77200,
      "grade": 0.2,
      "category": "kids",
      "categoryDetail": "코트",
      "releaseDate": "2020-04-27T18:37:16.292Z"
    },
    {
      "id": 2,
      "productName": "Refined Steel Ball",
      "productImage": "http://placeimg.com/640/480/fashion",
      "price": 27600,
      "grade": 0.2,
      "category": "men",
      "categoryDetail": "스웨터",
      "releaseDate": "2019-05-18T00:12:35.514Z"
    },
    {
      "id": 6,
      "productName": "Licensed Concrete Chips",
      "productImage": "http://placeimg.com/640/480/fashion",
      "price": 49900,
      "grade": 0.1,
      "category": "new",
      "categoryDetail": "코트",
      "releaseDate": "2019-02-13T18:15:31.279Z"
    },
    {
      "id": 9,
      "productName": "Rustic Plastic Car",
      "productImage": "http://placeimg.com/640/480/fashion",
      "price": 71500,
      "grade": 0,
      "category": "new",
      "categoryDetail": "코트",
      "releaseDate": "2018-06-02T09:45:49.709Z"
    }
  ]
}
